VoiPy/__init__.py
VoiPy/accurate_delay.py
VoiPy/helper.py
VoiPy/rtp.py
VoiPy/rtp_message.py
VoiPy/sip.py
VoiPy/sip_message.py
VoiPy/sip_methods.py
VoiPy/sip_receive.py
VoiPy/sip_template.py
VoiPy/status_handler.py
VoiPy/types.py
VoiPy/voip.py
VoiPy-1.4.8.dist-info/LICENSE
VoiPy-1.4.8.dist-info/METADATA
VoiPy-1.4.8.dist-info/WHEEL
VoiPy-1.4.8.dist-info/top_level.txt
VoiPy-1.4.8.dist-info/RECORD
