Metadata-Version: 2.1
Name: VoiPy
Version: 1.4.8
Summary: Voip package
Home-page: https://github.com/SeyedSaeidDehghani/VoiPy
Author: Seyed Saeid Dehghani
Author-email: s.saeid.dehghani@gmail.com
License: GNU GPLv3
Classifier: Programming Language :: Python :: 3.9
Classifier: License :: OSI Approved :: GNU General Public License v3 (GPLv3)
Classifier: Operating System :: Microsoft :: Windows :: Windows 10
Requires-Python: >=3.9.1
License-File: LICENSE
Requires-Dist: requests (>=2.26.0)
Requires-Dist: setuptools (>=42)
Requires-Dist: wheel
